symcon/__init__.py
symcon-0.0.2.dist-info/LICENSE
symcon-0.0.2.dist-info/METADATA
symcon-0.0.2.dist-info/WHEEL
symcon-0.0.2.dist-info/top_level.txt
symcon-0.0.2.dist-info/RECORD
