Metadata-Version: 2.1
Name: symcon
Version: 0.0.2
Summary: Python module for ip-symcon api calls
Home-page: https://github.com/thorstenMueller/symcon-python/
Author: Thorsten Mueller
Author-email: MrThorstenM@gmx.net
License: UNKNOWN
Platform: UNKNOWN
Classifier: Programming Language :: Python :: 3
Classifier: License :: OSI Approved :: MIT License
Classifier: Operating System :: OS Independent
Requires-Python: >=3.6
Requires-Dist: requests
